automaton_tools/__init__.py
automaton_tools/regex_parser/AST.py
automaton_tools/regex_parser/ASTVisitor.py
automaton_tools/regex_parser/Automaton.py
automaton_tools/regex_parser/AutomatonErrorListener.py
automaton_tools/regex_parser/AutomatonVisitor.py
automaton_tools/regex_parser/Components.py
automaton_tools/regex_parser/DFA.py
automaton_tools/regex_parser/NFA.py
automaton_tools/regex_parser/__init__.py
automaton_tools/regex_parser/grammar/RegexLexer.py
automaton_tools/regex_parser/grammar/RegexParser.py
automaton_tools/regex_parser/grammar/RegexVisitor.py
automaton_tools/regex_parser/grammar/__init__.py
automaton_tools-0.1.8.dist-info/METADATA
automaton_tools-0.1.8.dist-info/RECORD
automaton_tools-0.1.8.dist-info/WHEEL
automaton_tools-0.1.8.dist-info/top_level.txt
