Metadata-Version: 2.1
Name: automaton-tools
Version: 0.1.8
Summary: some algorithm implementations for automaton and regular expressions
Home-page: https://github.com/oneengineer/automaton_tools
Author: oneengineer
Author-email: oneengineer@gmail.com
License: UNKNOWN
Platform: UNKNOWN
Requires-Dist: antlr4-python3-runtime
